odoo/addons/sale_order_carrier_auto_assign/README.rst
odoo/addons/sale_order_carrier_auto_assign/__init__.py
odoo/addons/sale_order_carrier_auto_assign/__manifest__.py
odoo/addons/sale_order_carrier_auto_assign/i18n/es.po
odoo/addons/sale_order_carrier_auto_assign/i18n/it.po
odoo/addons/sale_order_carrier_auto_assign/i18n/sale_order_carrier_auto_assign.pot
odoo/addons/sale_order_carrier_auto_assign/models/__init__.py
odoo/addons/sale_order_carrier_auto_assign/models/res_company.py
odoo/addons/sale_order_carrier_auto_assign/models/res_config_settings.py
odoo/addons/sale_order_carrier_auto_assign/models/sale_order.py
odoo/addons/sale_order_carrier_auto_assign/models/sale_order_line.py
odoo/addons/sale_order_carrier_auto_assign/readme/CONFIGURE.md
odoo/addons/sale_order_carrier_auto_assign/readme/CONTRIBUTORS.md
odoo/addons/sale_order_carrier_auto_assign/readme/CREDITS.md
odoo/addons/sale_order_carrier_auto_assign/readme/DESCRIPTION.md
odoo/addons/sale_order_carrier_auto_assign/static/description/icon.png
odoo/addons/sale_order_carrier_auto_assign/static/description/index.html
odoo/addons/sale_order_carrier_auto_assign/tests/__init__.py
odoo/addons/sale_order_carrier_auto_assign/tests/test_sale_order_carrier_auto_assign.py
odoo/addons/sale_order_carrier_auto_assign/views/res_config_settings_views.xml
odoo/addons/sale_order_carrier_auto_assign/views/sale_order_views.xml
odoo_addon_sale_order_carrier_auto_assign-18.0.1.0.2.dist-info/METADATA
odoo_addon_sale_order_carrier_auto_assign-18.0.1.0.2.dist-info/WHEEL
odoo_addon_sale_order_carrier_auto_assign-18.0.1.0.2.dist-info/top_level.txt
odoo_addon_sale_order_carrier_auto_assign-18.0.1.0.2.dist-info/RECORD
